odoo/addons/project_wbs/README.rst
odoo/addons/project_wbs/__init__.py
odoo/addons/project_wbs/__manifest__.py
odoo/addons/project_wbs/hooks.py
odoo/addons/project_wbs/i18n/de.po
odoo/addons/project_wbs/i18n/es.po
odoo/addons/project_wbs/i18n/fr.po
odoo/addons/project_wbs/i18n/it.po
odoo/addons/project_wbs/i18n/project_wbs.pot
odoo/addons/project_wbs/i18n/pt_BR.po
odoo/addons/project_wbs/i18n/sl.po
odoo/addons/project_wbs/models/__init__.py
odoo/addons/project_wbs/models/account_analytic_account.py
odoo/addons/project_wbs/models/project_project.py
odoo/addons/project_wbs/readme/CONTRIBUTORS.rst
odoo/addons/project_wbs/readme/DESCRIPTION.rst
odoo/addons/project_wbs/readme/ROADMAP.rst
odoo/addons/project_wbs/readme/USAGE.rst
odoo/addons/project_wbs/static/description/icon.png
odoo/addons/project_wbs/static/description/index.html
odoo/addons/project_wbs/tests/__init__.py
odoo/addons/project_wbs/tests/test_project_wbs.py
odoo/addons/project_wbs/view/account_analytic_account_view.xml
odoo/addons/project_wbs/view/project_project_view.xml
odoo_addon_project_wbs-15.0.1.2.0.2.dist-info/METADATA
odoo_addon_project_wbs-15.0.1.2.0.2.dist-info/WHEEL
odoo_addon_project_wbs-15.0.1.2.0.2.dist-info/top_level.txt
odoo_addon_project_wbs-15.0.1.2.0.2.dist-info/RECORD
