Metadata-Version: 2.1
Name: odoo-addon-project_wbs
Version: 15.0.1.2.0.2
Summary: Apply Work Breakdown Structure
Home-page: https://github.com/OCA/project
Author: Matmoz d.o.o., Luxim d.o.o., Deneroteam, ForgeFlow, Odoo Community Association (OCA)
Author-email: support@odoo-community.org
License: AGPL-3
Classifier: Programming Language :: Python
Classifier: Framework :: Odoo
Classifier: Framework :: Odoo :: 15.0
Classifier: License :: OSI Approved :: GNU Affero General Public License v3
Requires-Python: >=3.8
Requires-Dist: odoo-addon-account-analytic-parent<15.1dev,>=15.0dev
Requires-Dist: odoo-addon-account-analytic-sequence<15.1dev,>=15.0dev
Requires-Dist: odoo<15.1dev,>=15.0a
